spanking/__init__.py
spanking/llm.py
spanking/main.py
spanking-1.1.dist-info/LICENSE
spanking-1.1.dist-info/METADATA
spanking-1.1.dist-info/WHEEL
spanking-1.1.dist-info/entry_points.txt
spanking-1.1.dist-info/top_level.txt
spanking-1.1.dist-info/RECORD
