Metadata-Version: 2.1
Name: spanking
Version: 1.1
Home-page: https://github.com/rishiraj/spanking
Author: Rishiraj Acharya
Author-email: heyrishiraj@gmail.com
License: Apache 2.0
License-File: LICENSE
